vizpool/__init__.py
vizpool/utils/__init__.py
vizpool/utils/interactive.py
vizpool/utils/static.py
vizpool-0.0.6.dist-info/LICENSE
vizpool-0.0.6.dist-info/METADATA
vizpool-0.0.6.dist-info/WHEEL
vizpool-0.0.6.dist-info/top_level.txt
vizpool-0.0.6.dist-info/RECORD
