Metadata-Version: 2.1
Name: vizpool
Version: 0.0.6
Summary: A high-level python API with low-code support for Data Visualization
Home-page: https://github.com/Hassi34/vizpool
Author: Hassi34
Author-email: hasnainmehmood3435@gmail.com
Project-URL: Bug Tracker, https://github.com/Hassi34/vizpool/issues
Classifier: Programming Language :: Python :: 3
Classifier: License :: OSI Approved :: MIT License
Classifier: Operating System :: OS Independent
Requires-Python: >=3.7
License-File: LICENSE
Requires-Dist: plotly (>=5.8.0)
